README.md
setup.py
python_utils_forsythetony.egg-info/PKG-INFO
python_utils_forsythetony.egg-info/SOURCES.txt
python_utils_forsythetony.egg-info/dependency_links.txt
python_utils_forsythetony.egg-info/top_level.txt
utils/__init__.py
utils/dummydata.py
utils/os.py
utils/string.py
utils/timing.py